MANIFEST.in
README.rst
setup.py
vais/AI_sample_game.py
vais/__init__.py
vais/battle.py
vais/build_internet.py
vais/character.py
vais/envirosim.py
vais/planet.py
vais/run.py
vais/simulation_types.py
vais/simulator.py
vais/world_generator.py
vais/worlds.py
vais.egg-info/PKG-INFO
vais.egg-info/SOURCES.txt
vais.egg-info/dependency_links.txt
vais.egg-info/requires.txt
vais.egg-info/top_level.txt
vais/data/__init__.py
vais/data/battle.rules
vais/data/christmas-dinner.rules
vais/data/display.rules
vais/data/ref_classes.csv
vais/data/ref_materials.csv
vais/data/ref_monsters.csv
vais/data/ref_objects.csv
vais/data/ref_races.csv
vais/data/ref_skills.csv
vais/data/ref_stats.csv
vais/data/ref_stories.csv
vais/data/terrain.rules
vais/data/worlds/Divitie.txt
vais/data/worlds/ExamplePlanet.txt
vais/data/worlds/MyPlanet.txt
vais/data/worlds/high_lava.txt
vais/data/worlds/high_seed.txt
vais/data/worlds/low_lava.txt
vais/data/worlds/low_seed.txt
vais/data/worlds/planet_med.txt
vais/data/worlds/planet_samples.csv
vais/data/worlds/planet_small.txt
vais/data/worlds/quick_planet.txt
vais/data/worlds/vais_world.txt
vais/data/worlds/vais_world_traversed.txt
vais/examples/__init__.py
vais/examples/example_noise.py
vais/npc/__init__.py
vais/npc/bandits.py
vais/npc/web_users.py
vais/npc/zombies.py