Metadata-Version: 1.1
Name: vais
Version: 0.0.7
Summary: Virtual AI Simulator runs agents and players across multiple worlds
Home-page: https://github.com/acutesoftware/virtual-AI-simulator
Author: Duncan Murray
Author-email: djmurray@acutesoftware.com.au
License: LICENSE.txt
Platform: UNKNOWN
Classifier: Development Status :: 2 - Pre-Alpha
Classifier: Environment :: Web Environment
Classifier: Programming Language :: Python :: 3
Classifier: Programming Language :: Python :: 3.4
Classifier: Intended Audience :: Developers
Classifier: Natural Language :: English
Classifier: Operating System :: OS Independent
Classifier: Topic :: Scientific/Engineering :: Artificial Intelligence
Classifier: Topic :: Software Development :: Libraries :: Python Modules
Classifier: Topic :: Games/Entertainment :: Simulation
